package/__init__.py
package/main.py
string_util_project-1.0.0.dist-info/LICENCE.txt
string_util_project-1.0.0.dist-info/METADATA
string_util_project-1.0.0.dist-info/WHEEL
string_util_project-1.0.0.dist-info/entry_points.txt
string_util_project-1.0.0.dist-info/top_level.txt
string_util_project-1.0.0.dist-info/RECORD
